[
  [
    {
      "character": "THELMA",
      "dialogue": "She got scared, your mother. We were all scared.",
      "movie": "thelma"
    },
    {
      "character": "ALAN",
      "dialogue": "I wasn\u2019t quite as scared. For the record.",
      "movie": "thelma"
    },
    {
      "character": "THELMA",
      "dialogue": "See what happens when you get a call, buddy.",
      "movie": "thelma"
    },
    {
      "character": "ALAN",
      "dialogue": "I wouldn\u2019t be fooled. My mind is sharp as a tac.",
      "movie": "thelma"
    },
    {
      "character": "THELMA",
      "dialogue": "Wha?",
      "movie": "thelma"
    },
    {
      "character": "ALAN",
      "dialogue": "I said I wouldn\u2019t be fooled. My mind is sharp as a tac!",
      "movie": "thelma"
    },
    {
      "character": "THELMA",
      "dialogue": "What\u2019s he saying?",
      "movie": "thelma"
    }
  ],
  [
    {
      "character": "THELMA",
      "dialogue": "What\u2019s the joke, Alan?",
      "movie": "thelma"
    },
    {
      "character": "ALAN",
      "dialogue": "Never mind.",
      "movie": "thelma"
    }
  ],
  [
    {
      "character": "ALAN",
      "dialogue": "Waze says 12 minutes via Chandler and Colfax.",
      "movie": "thelma"
    },
    {
      "character": "THELMA",
      "dialogue": "Look at this... who created this? Who thought it up? A plug for a car. Electricity goes through. Makes it run. And what is electricity? It boggles the mind...",
      "movie": "thelma"
    },
    {
      "character": "THELMA",
      "dialogue": "I think I know her...",
      "movie": "thelma"
    }
  ],
  [
    {
      "character": "THELMA",
      "dialogue": "I\u2019m alright, darling. I\u2019m alright.",
      "movie": "thelma"
    },
    {
      "character": "ALAN",
      "dialogue": "You drove.",
      "movie": "thelma"
    }
  ]
]