[
  [
    {
      "character": "RACHEL",
      "dialogue": "Vi...c...to...or.",
      "movie": "his-three-daughters"
    },
    {
      "character": "RACHEL",
      "dialogue": "Damn, Victor. What are you doin\u2019? You fucked my whole shit up.",
      "movie": "his-three-daughters"
    },
    {
      "character": "VICTOR",
      "dialogue": "You shouldn\u2019t be doing your whole shit here. That\u2019s the problem.",
      "movie": "his-three-daughters"
    },
    {
      "character": "RACHEL",
      "dialogue": "Shit\u2019s legal now. What are you stuck in the nineties when you last blazed?",
      "movie": "his-three-daughters"
    },
    {
      "character": "VICTOR",
      "dialogue": "Please. I smoke every night, but when I get home, inside my own apartment. You know how it is here. These people lose it when someone smokes a cigarette out here. They ask me to call the cops. It\u2019s crazy. Why aren\u2019t you inside where I can just call you with a complaint and you can tell me to go fuck myself?",
      "movie": "his-three-daughters"
    },
    {
      "character": "RACHEL",
      "dialogue": "Okay. Last. One....",
      "movie": "his-three-daughters"
    },
    {
      "character": "RACHEL",
      "dialogue": "My..bitch...ass...sister. She\u2019s trying to say the smoke is killing our dad.",
      "movie": "his-three-daughters"
    },
    {
      "character": "VICTOR",
      "dialogue": "How is Vinnie?",
      "movie": "his-three-daughters"
    },
    {
      "character": "RACHEL",
      "dialogue": "He\u2019s fucking dying! But not from my weed smoke! She\u2019s just a fucking... It\u2019s got to be something. Now she got me out here, trying to chill, and getting yelled at\u2014I know, I know\u2014I don\u2019t mean any disrespect. You know I love you. But she\u2019s who you should be yelling at, not me. I\u2019m just trying to maintain, y\u2019know?",
      "movie": "his-three-daughters"
    }
  ],
  [
    {
      "character": "VICTOR",
      "dialogue": "Rachel\u2014",
      "movie": "his-three-daughters"
    },
    {
      "character": "RACHEL",
      "dialogue": "I love you Victor, but truly, fuck off. Call whoever you want, do whatever you want. I really do not give a fuck. Shit is legal is all I know.",
      "movie": "his-three-daughters"
    },
    {
      "character": "RACHEL",
      "dialogue": "Goddamn right, get the fuck out of here with that bullshit.",
      "movie": "his-three-daughters"
    },
    {
      "character": "RACHEL",
      "dialogue": "How you doing? Doing ok?",
      "movie": "his-three-daughters"
    }
  ],
  [
    {
      "character": "RACHEL",
      "dialogue": "Doing okay.",
      "movie": "his-three-daughters"
    },
    {
      "character": "VICTOR",
      "dialogue": "How\u2019s your dad doing?",
      "movie": "his-three-daughters"
    },
    {
      "character": "RACHEL",
      "dialogue": "Hanging in. Still here.",
      "movie": "his-three-daughters"
    },
    {
      "character": "VICTOR",
      "dialogue": "That\u2019s good.",
      "movie": "his-three-daughters"
    },
    {
      "character": "RACHEL",
      "dialogue": "Yup. Thanks.",
      "movie": "his-three-daughters"
    },
    {
      "character": "VICTOR",
      "dialogue": "You know what I\u2019m supposed to be telling you, right? About smoking out here? Let\u2019s just say that I did, okay?",
      "movie": "his-three-daughters"
    },
    {
      "character": "RACHEL",
      "dialogue": "Yup, yup. Thanks.",
      "movie": "his-three-daughters"
    }
  ],
  [
    {
      "character": "VICTOR",
      "dialogue": "How you doing, Rach?",
      "movie": "his-three-daughters"
    },
    {
      "character": "VICTOR",
      "dialogue": "I heard the news. I\u2019m sorry. You hanging in there okay?",
      "movie": "his-three-daughters"
    },
    {
      "character": "RACHEL",
      "dialogue": "Yeah, I\u2019m doing ok. Thanks, Victor.",
      "movie": "his-three-daughters"
    }
  ]
]